{"color":"DEFAULT","isTrashed":false,"isPinned":false,"isArchived":false,"annotations":[{"description":"","source":"WEBLINK","title":"【WEB予約限定】成田発｜ユナイテッド航空＜往路：夜発/復路：午後発＞グアム4日間≪星野リゾート・リゾナーレ・グアム≫(9WG4DHK-DBK-P)｜阪急交通社","url":"https://www.hankyu-travel.com/tour/detail_i.php?p_hei=12&p_course_id=9WG4DHK-DBK-P"}],"textContent":"https://www.hankyu-travel.com/tour/detail_i.php?p_course_id=9WG4DHK-DBK-P&p_hei=12","title":"","userEditedTimestampUsec":1720611712824000,"createdTimestampUsec":1720611712824000,"textContentHtml":"<p dir=\"ltr\" style=\"line-height:1.38;margin-top:0.0pt;margin-bottom:0.0pt;\"><span style=\"font-size:7.2pt;font-family:'Google Sans';color:#000000;background-color:transparent;font-weight:400;font-style:normal;font-variant:normal;text-decoration:none;vertical-align:baseline;white-space:pre;white-space:pre-wrap;\">https://www.hankyu-travel.com/tour/detail_i.php?p_course_id=9WG4DHK-DBK-P&amp;p_hei=12<\/span><\/p>"}