{"color":"DEFAULT","isTrashed":false,"isPinned":false,"isArchived":false,"annotations":[{"description":"楽しい旅行でいつも頭を抱えるのがお土産選び！ そこで香港に住んで40年の還暦料理人の私「モリシェフ」がコロナの影響を再確","source":"WEBLINK","title":"香港でおすすめのお土産は？楽しく買って必ず喜ばれる最新の21選！｜香港のモリシェフ HK最新情報","url":"https://proms316-hk.com/2021/07/10/hongkong-omiyage21/"}],"textContent":"https://proms316-hk.com/2021/07/10/hongkong-omiyage21/","title":"","userEditedTimestampUsec":1692023047324000,"createdTimestampUsec":1692023047324000,"textContentHtml":"<p dir=\"ltr\" style=\"line-height:1.38;margin-top:0.0pt;margin-bottom:0.0pt;\"><span style=\"font-size:7.2pt;font-family:'Google Sans';color:#000000;background-color:transparent;font-weight:400;font-style:normal;font-variant:normal;text-decoration:none;vertical-align:baseline;white-space:pre;white-space:pre-wrap;\">https://proms316-hk.com/2021/07/10/hongkong-omiyage21/<\/span><\/p>"}