{"color":"DEFAULT","isTrashed":false,"isPinned":false,"isArchived":false,"textContent":"https://pl.aliexpress.com/item/1005005627005453.html?src=google&aff_fcid=5ed41d17ca644425aa9c1a2e47cdd0c1-1721042198143-08045-UneMJZVf&aff_fsk=UneMJZVf&aff_platform=aaf&sk=UneMJZVf&aff_trace_key=5ed41d17ca644425aa9c1a2e47cdd0c1-1721042198143-08045-UneMJZVf&terminal_id=47a9079f7ede4039bfee9f15e92e3b33&afSmartRedirect=n","title":"","userEditedTimestampUsec":1721042583276000,"createdTimestampUsec":1721042583276000,"textContentHtml":"<p dir=\"ltr\" style=\"line-height:1.38;margin-top:0.0pt;margin-bottom:0.0pt;\"><span style=\"font-size:7.2pt;font-family:'Google Sans';color:#000000;background-color:transparent;font-weight:400;font-style:normal;font-variant:normal;text-decoration:none;vertical-align:baseline;white-space:pre;white-space:pre-wrap;\">https://pl.aliexpress.com/item/1005005627005453.html?src=google&amp;aff_fcid=5ed41d17ca644425aa9c1a2e47cdd0c1-1721042198143-08045-UneMJZVf&amp;aff_fsk=UneMJZVf&amp;aff_platform=aaf&amp;sk=UneMJZVf&amp;aff_trace_key=5ed41d17ca644425aa9c1a2e47cdd0c1-1721042198143-08045-UneMJZVf&amp;terminal_id=47a9079f7ede4039bfee9f15e92e3b33&amp;afSmartRedirect=n<\/span><\/p>"}